statslib.cpython-38-darwin.so
statslib-0.0.4.dist-info/LICENSE
statslib-0.0.4.dist-info/METADATA
statslib-0.0.4.dist-info/WHEEL
statslib-0.0.4.dist-info/top_level.txt
statslib-0.0.4.dist-info/RECORD
