Metadata-Version: 2.1
Name: statslib
Version: 0.0.4
Summary: Bindings for StatsLib (https://github.com/kthohr/stats)
Home-page: https://github.com/aforren1/pystatslib
Author: Alexander Forrence
Author-email: alex.forrence@gmail.com
License: UNKNOWN
Platform: UNKNOWN
Classifier: License :: OSI Approved :: Apache Software License
Classifier: Development Status :: 4 - Beta
Classifier: Intended Audience :: Science/Research
Classifier: Programming Language :: Python :: 3
Classifier: Programming Language :: Python :: 3.6
Classifier: Programming Language :: Python :: 3.7
Classifier: Programming Language :: Python :: 3.8
Classifier: Programming Language :: Python :: 3.9
Classifier: Programming Language :: Python :: 3.10
